baseball_scorecard/__init__.py
baseball_scorecard/baseball_scorecard.py
baseball_scorecard/metapost/__init__.py
baseball_scorecard/metapost/metapost_builder.py
baseball_scorecard/metapost/templates/final_scorecard_template.tex
baseball_scorecard/metapost/templates/team_scorecard_template.mp
baseball_scorecard/misc/__init__.py
baseball_scorecard/misc/game_info.py
baseball_scorecard/misc/umpire.py
baseball_scorecard/plays/__init__.py
baseball_scorecard/plays/at_bat.py
baseball_scorecard/plays/inning.py
baseball_scorecard/plays/labeling/advance.py
baseball_scorecard/plays/labeling/at_base.py
baseball_scorecard/plays/labeling/no_ab.py
baseball_scorecard/plays/labeling/out.py
baseball_scorecard/plays/labeling/pitch.py
baseball_scorecard/plays/labeling/thrown_out.py
baseball_scorecard/plays/labeling/waybase.py
baseball_scorecard/plays/substitution/batter.py
baseball_scorecard/plays/substitution/fielder.py
baseball_scorecard/plays/substitution/pitcher.py
baseball_scorecard/stats/__init__.py
baseball_scorecard/stats/batter_stats.py
baseball_scorecard/stats/inning_stats.py
baseball_scorecard/stats/pitcher_stats.py
baseball_scorecard/stats/team_stats.py
baseball_scorecard/team/__init__.py
baseball_scorecard/team/lineup.py
baseball_scorecard/team/pitcher_lineup.py
baseball_scorecard/team/player.py
baseball_scorecard/team/reserves.py
baseball_scorecard/team/roster.py
baseball_scorecard/team/team.py
baseball_scorecard-0.1.2.dist-info/LICENSE
baseball_scorecard-0.1.2.dist-info/METADATA
baseball_scorecard-0.1.2.dist-info/WHEEL
baseball_scorecard-0.1.2.dist-info/RECORD
