Metadata-Version: 2.1
Name: baseball_scorecard
Version: 0.1.2
Summary: API to programatically generate baseball scorecards as PDFs.
License: GPL-3.0-or-later
Author: Vicyorus
Author-email: andres.chaves.diaz@gmail.com
Requires-Python: >=3.10,<4.0
Classifier: License :: OSI Approved :: GNU General Public License v3 or later (GPLv3+)
Classifier: Programming Language :: Python :: 3
Classifier: Programming Language :: Python :: 3.10
Classifier: Programming Language :: Python :: 3.11
Classifier: Programming Language :: Python :: 3.12
